pff-1.0.2.dist-info/licenses/LICENSE
pff_omar_arabi/__init__.py
pff_omar_arabi/__main__.py
pff_omar_arabi/cli/__init__.py
pff_omar_arabi/cli/cli.py
pff_omar_arabi/fuzzy_search/__init__.py
pff_omar_arabi/fuzzy_search/fuzzy_search.py
pff_omar_arabi/util/__init__.py
pff_omar_arabi/util/show_entries.py
pff-1.0.2.dist-info/METADATA
pff-1.0.2.dist-info/WHEEL
pff-1.0.2.dist-info/entry_points.txt
pff-1.0.2.dist-info/top_level.txt
pff-1.0.2.dist-info/RECORD
