Metadata-Version: 2.4
Name: pff
Version: 1.0.2
Summary: a fuzzy search for files and diretories
Maintainer-email: Omar Arabi <omarbuisness7@gmail.com>
License-Expression: MIT
Project-URL: Repository, https://github.com/Omar-Arabi1/pff
Requires-Python: >=3.13
License-File: LICENSE
Requires-Dist: build>=1.3.0
Requires-Dist: colorama>=0.4.6
Requires-Dist: pytest>=8.4.1
Requires-Dist: twine>=6.1.0
Dynamic: license-file
